{
    "IMAGE_INFO": {
        "FILE_NAME": "942161@0_01002_220906_P1_T3__0965.jpg",
        "DATE": "2022-10-21 11:34:04",
        "RESOLUTION": "1920 x 1080",
        "IMAGE_PHOTOGRAPHER": "강윤정",
        "FOCUS_DISTANCE": "5.6",
        "EXPOSURE_TIME": "1/250",
        "SENSITIVITY_ISO": "6400",
        "PLACE": "삼오자원",
        "REGION_NAME": null,
        "Direction": "0",
        "HEIGHT": "100",
        "DAY/NIGHT": "주간",
        "WEATHER": "맑음",
        "IMAGE_HEIGHT": 1080,
        "IMAGE_WIDTH": 1920,
        "IMAGE_SIZE": "562.3 KB"
    },
    "ANNOTATION_INFO": [
        {
            "ID": "1",
            "CLASS": "금속캔",
            "DETAILS": "알루미늄캔",
            "DAMAGE": "찌그러짐",
            "DIRTINESS": "오염없음",
            "COVER": "없음",
            "TRANSPARENCY": "불투명",
            "SHAPE": "뚱뚱한 원통형",
            "SHAPE_TYPE": "BOX",
            "POINTS": [
                [
                    270.230966015625,
                    202.17977992466516,
                    269.3705142857143,
                    256.11428571428576
                ]
            ]
        },
        {
            "ID": "2",
            "CLASS": "금속캔",
            "DETAILS": "알루미늄캔",
            "DAMAGE": "찌그러짐",
            "DIRTINESS": "오염없음",
            "COVER": "없음",
            "TRANSPARENCY": "불투명",
            "SHAPE": "뚱뚱한 원통형",
            "SHAPE_TYPE": "BOX",
            "POINTS": [
                [
                    558.8912529184822,
                    224.2985502103795,
                    228.35237595428566,
                    247.97886171428584
                ]
            ]
        },
        {
            "ID": "3",
            "CLASS": "금속캔",
            "DETAILS": "알루미늄캔",
            "DAMAGE": "찌그러짐",
            "DIRTINESS": "오염없음",
            "COVER": "없음",
            "TRANSPARENCY": "불투명",
            "SHAPE": "뚱뚱하고 긴 원통형",
            "SHAPE_TYPE": "BOX",
            "POINTS": [
                [
                    644.1547374441961,
                    770.8614942103795,
                    396.946285714286,
                    309.13850578962047
                ]
            ]
        },
        {
            "ID": "4",
            "CLASS": "금속캔",
            "DETAILS": "알루미늄캔",
            "DAMAGE": "찌그러짐",
            "DIRTINESS": "오염없음",
            "COVER": "없음",
            "TRANSPARENCY": "불투명",
            "SHAPE": "뚱뚱한 원통형",
            "SHAPE_TYPE": "BOX",
            "POINTS": [
                [
                    1171.4415945870537,
                    791.0883513532366,
                    317.21142857142877,
                    279.8724342857141
                ]
            ]
        }
    ]
}